setup.py
bin/payara
payara/__init__.py
payara/repo.py
payara/s3.py
payara/server.py
payara.egg-info/PKG-INFO
payara.egg-info/SOURCES.txt
payara.egg-info/dependency_links.txt
payara.egg-info/requires.txt
payara.egg-info/top_level.txt