Metadata-Version: 1.0
Name: payara
Version: 0.0.1
Summary: A tool for rapid web development
Home-page: https://github.com/zeekay/payara
Author: Zach Kelling
Author-email: zeekayy@gmail.com
License: UNKNOWN
Platform: UNKNOWN
